Fluxed/__init__.py
Fluxed/distributions.py
Fluxed/match.py
Fluxed/shapes.py
fluxed-1.0.1.dist-info/licenses/LICENSE
fluxed-1.0.1.dist-info/METADATA
fluxed-1.0.1.dist-info/WHEEL
fluxed-1.0.1.dist-info/top_level.txt
fluxed-1.0.1.dist-info/RECORD
