Metadata-Version: 2.4
Name: Fluxed
Version: 1.0.1
Summary: A Python library for simulating and analyzing fluxes in complex systems.
Author-email: Rishabh Garg <rishabh@rishabhgarg.dev>
License-Expression: GPL-3.0-or-later
Classifier: Development Status :: 3 - Alpha
Classifier: Intended Audience :: Science/Research
Classifier: Programming Language :: Python :: 3.11
Classifier: Programming Language :: Python :: 3.12
Classifier: Programming Language :: Python :: 3.13
Classifier: Topic :: Scientific/Engineering
Requires-Python: >=3.11
License-File: LICENSE
Requires-Dist: numpy
Requires-Dist: scipy
Provides-Extra: dev
Requires-Dist: pytest; extra == "dev"
Dynamic: license-file
